embost/__init__.py
embost/embost.py
embost-1.0.0.dist-info/licenses/LICENSE
embost-1.0.0.dist-info/WHEEL
embost-1.0.0.dist-info/METADATA
embost-1.0.0.dist-info/RECORD
